README.md
setup.py
onehundredone/__init__.py
onehundredone/authorization.py
onehundredone/friend.py
onehundredone/game.py
onehundredone/onehundredone.py
onehundredone/socket_listener.py
onehundredone/utils/__init__.py
onehundredone/utils/objects.py
onehundredone_online.py.egg-info/PKG-INFO
onehundredone_online.py.egg-info/SOURCES.txt
onehundredone_online.py.egg-info/dependency_links.txt
onehundredone_online.py.egg-info/requires.txt
onehundredone_online.py.egg-info/top_level.txt