Metadata-Version: 2.1
Name: onehundredone-online.py
Version: 2.0.0
Summary: A library to create 101 Online bots.
Home-page: https://github.com/Zakovskiy/onehundredone_online.py
Author: Zakovskiy
Author-email: gogrugu@gmail.com
License: MIT
Download-URL: https://github.com/Zakovskiy/onehundredone_online.py/tarball/master
Keywords: durak,online,onehundredone_online.py,onehundredone.py,101-bot,101.py,rstgame,rstgames,api,socket,python,python3,python3.x,zakovskiy,official
Platform: UNKNOWN
